greenmining/__init__.py
greenmining/__main__.py
greenmining/gsf_patterns.py
greenmining/utils.py
greenmining/analyzers/__init__.py
greenmining/analyzers/code_diff_analyzer.py
greenmining/analyzers/metrics_power_correlator.py
greenmining/analyzers/statistical_analyzer.py
greenmining/analyzers/temporal_analyzer.py
greenmining/controllers/__init__.py
greenmining/controllers/repository_controller.py
greenmining/energy/__init__.py
greenmining/energy/base.py
greenmining/energy/carbon_reporter.py
greenmining/energy/codecarbon_meter.py
greenmining/energy/cpu_meter.py
greenmining/energy/rapl.py
greenmining/models/__init__.py
greenmining/models/aggregated_stats.py
greenmining/models/analysis_result.py
greenmining/models/commit.py
greenmining/models/repository.py
greenmining/services/__init__.py
greenmining/services/commit_extractor.py
greenmining/services/data_aggregator.py
greenmining/services/data_analyzer.py
greenmining/services/github_graphql_fetcher.py
greenmining/services/local_repo_analyzer.py
greenmining/services/reports.py
greenmining-1.2.5.dist-info/licenses/LICENSE
greenmining-1.2.5.dist-info/METADATA
greenmining-1.2.5.dist-info/WHEEL
greenmining-1.2.5.dist-info/top_level.txt
greenmining-1.2.5.dist-info/RECORD
