Metadata-Version: 2.4
Name: greenmining
Version: 1.2.5
Summary: An empirical Python library for Mining Software Repositories (MSR) in Green IT research
Author-email: Adam Bouafia <a.bouafia@student.vu.nl>
License: MIT
Project-URL: Homepage, https://github.com/adam-bouafia/greenmining
Project-URL: Documentation, https://github.com/adam-bouafia/greenmining#readme
Project-URL: Linkedin, https://www.linkedin.com/in/adam-bouafia/
Project-URL: Repository, https://github.com/adam-bouafia/greenmining
Project-URL: Issues, https://github.com/adam-bouafia/greenmining/issues
Project-URL: Changelog, https://github.com/adam-bouafia/greenmining/blob/main/CHANGELOG.md
Keywords: green-software,gsf,msr,mining-software-repositories,green-it,sustainability,carbon-footprint,energy-efficiency,repository-analysis,github-analysis,pydriller,empirical-software-engineering
Classifier: Development Status :: 3 - Alpha
Classifier: Intended Audience :: Developers
Classifier: Intended Audience :: Science/Research
Classifier: Topic :: Software Development :: Quality Assurance
Classifier: Topic :: Scientific/Engineering :: Information Analysis
Classifier: License :: OSI Approved :: MIT License
Classifier: Programming Language :: Python :: 3
Classifier: Programming Language :: Python :: 3.9
Classifier: Programming Language :: Python :: 3.10
Classifier: Programming Language :: Python :: 3.11
Classifier: Programming Language :: Python :: 3.12
Classifier: Programming Language :: Python :: 3.13
Classifier: Operating System :: OS Independent
Requires-Python: >=3.9
License-File: LICENSE
Requires-Dist: PyGithub
Requires-Dist: PyDriller
Requires-Dist: pandas
Requires-Dist: colorama
Requires-Dist: tabulate
Requires-Dist: tqdm
Requires-Dist: matplotlib
Requires-Dist: plotly
Requires-Dist: python-dotenv
Requires-Dist: requests
Provides-Extra: dev
Requires-Dist: pytest; extra == "dev"
Requires-Dist: pytest-cov; extra == "dev"
Requires-Dist: pytest-mock; extra == "dev"
Requires-Dist: black; extra == "dev"
Requires-Dist: ruff; extra == "dev"
Requires-Dist: mypy; extra == "dev"
Requires-Dist: build; extra == "dev"
Requires-Dist: twine; extra == "dev"
Provides-Extra: energy
Requires-Dist: psutil; extra == "energy"
Requires-Dist: codecarbon; extra == "energy"
Provides-Extra: docs
Requires-Dist: sphinx; extra == "docs"
Requires-Dist: sphinx-rtd-theme; extra == "docs"
Requires-Dist: myst-parser; extra == "docs"
Dynamic: license-file
